compressjpg
