Metadata-Version: 1.0
Name: compressjpg
Version: 0.2
Summary: Compressing jpg files with SVD algorithm
Home-page: https://github.com/tworitdash/compressjpg
Author: Tworit Dash
Author-email: tworitdash@gmail.com
License: MIT
Platform: UNKNOWN
